{"trial_id": "0100", "hyperparameters": {"space": [{"class_name": "Choice", "config": {"name": "activation", "default": "relu", "conditions": [], "values": ["relu", "tanh", "sigmoid"], "ordered": false}}, {"class_name": "Int", "config": {"name": "num_layers", "default": null, "conditions": [], "min_value": 1, "max_value": 20, "step": 1, "sampling": "linear"}}, {"class_name": "Int", "config": {"name": "units_0", "default": null, "conditions": [], "min_value": 1, "max_value": 20, "step": 2, "sampling": "linear"}}, {"class_name": "Int", "config": {"name": "units_1", "default": null, "conditions": [], "min_value": 1, "max_value": 20, "step": 2, "sampling": "linear"}}, {"class_name": "Int", "config": {"name": "units_2", "default": null, "conditions": [], "min_value": 1, "max_value": 20, "step": 2, "sampling": "linear"}}, {"class_name": "Int", "config": {"name": "units_3", "default": null, "conditions": [], "min_value": 1, "max_value": 20, "step": 2, "sampling": "linear"}}, {"class_name": "Int", "config": {"name": "units_4", "default": null, "conditions": [], "min_value": 1, "max_value": 20, "step": 2, "sampling": "linear"}}, {"class_name": "Int", "config": {"name": "units_5", "default": null, "conditions": [], "min_value": 1, "max_value": 20, "step": 2, "sampling": "linear"}}, {"class_name": "Int", "config": {"name": "units_6", "default": null, "conditions": [], "min_value": 1, "max_value": 20, "step": 2, "sampling": "linear"}}, {"class_name": "Int", "config": {"name": "units_7", "default": null, "conditions": [], "min_value": 1, "max_value": 20, "step": 2, "sampling": "linear"}}, {"class_name": "Int", "config": {"name": "units_8", "default": null, "conditions": [], "min_value": 1, "max_value": 20, "step": 2, "sampling": "linear"}}, {"class_name": "Int", "config": {"name": "units_9", "default": null, "conditions": [], "min_value": 1, "max_value": 20, "step": 2, "sampling": "linear"}}, {"class_name": "Int", "config": {"name": "units_10", "default": null, "conditions": [], "min_value": 1, "max_value": 20, "step": 2, "sampling": "linear"}}, {"class_name": "Int", "config": {"name": "units_11", "default": null, "conditions": [], "min_value": 1, "max_value": 20, "step": 2, "sampling": "linear"}}, {"class_name": "Int", "config": {"name": "units_12", "default": null, "conditions": [], "min_value": 1, "max_value": 20, "step": 2, "sampling": "linear"}}, {"class_name": "Int", "config": {"name": "units_13", "default": null, "conditions": [], "min_value": 1, "max_value": 20, "step": 2, "sampling": "linear"}}, {"class_name": "Int", "config": {"name": "units_14", "default": null, "conditions": [], "min_value": 1, "max_value": 20, "step": 2, "sampling": "linear"}}, {"class_name": "Int", "config": {"name": "units_15", "default": null, "conditions": [], "min_value": 1, "max_value": 20, "step": 2, "sampling": "linear"}}, {"class_name": "Int", "config": {"name": "units_16", "default": null, "conditions": [], "min_value": 1, "max_value": 20, "step": 2, "sampling": "linear"}}, {"class_name": "Int", "config": {"name": "units_17", "default": null, "conditions": [], "min_value": 1, "max_value": 20, "step": 2, "sampling": "linear"}}, {"class_name": "Int", "config": {"name": "units_18", "default": null, "conditions": [], "min_value": 1, "max_value": 20, "step": 2, "sampling": "linear"}}, {"class_name": "Int", "config": {"name": "units_19", "default": null, "conditions": [], "min_value": 1, "max_value": 20, "step": 2, "sampling": "linear"}}], "values": {"activation": "tanh", "num_layers": 17, "units_0": 7, "units_1": 9, "units_2": 11, "units_3": 1, "units_4": 9, "units_5": 15, "units_6": 1, "units_7": 5, "units_8": 13, "units_9": 19, "units_10": 7, "units_11": 5, "units_12": 7, "units_13": 11, "units_14": 13, "units_15": 13, "units_16": 5, "units_17": 13, "units_18": 15, "units_19": 9, "tuner/epochs": 2, "tuner/initial_epoch": 0, "tuner/bracket": 3, "tuner/round": 0}}, "metrics": {"metrics": {"accuracy": {"direction": "max", "observations": [{"value": [0.6203584671020508], "step": 1}]}, "loss": {"direction": "min", "observations": [{"value": [0.6546140909194946], "step": 1}]}, "precision": {"direction": "max", "observations": [{"value": [0.6131114959716797], "step": 1}]}, "val_accuracy": {"direction": "max", "observations": [{"value": [0.6201013922691345], "step": 1}]}, "val_loss": {"direction": "min", "observations": [{"value": [0.6557739973068237], "step": 1}]}, "val_precision": {"direction": "max", "observations": [{"value": [0.6221116185188293], "step": 1}]}}}, "score": 0.6201013922691345, "best_step": 1, "status": "COMPLETED", "message": null}